{
    "type": "mssql",
    "host": "unah-rafaelbautista.database.windows.net",
    "port": 1433,
    "username": "Rafa-admin",
    "password": "Olimpia.2012",
    "database": "BD_Ingreso_Vehiculo",
    "options":{
        "synchronize": true,
        "logging": false,
        "encrypt": true,
        "enableArithAbort": true
    },
    "entities":[
        "src/entity/**/*.ts"
    ],
    "migrations": [
        "src/migration/**/*.ts"
    ],
    "subscribers":[
        "src/subscriber/**/*.ts"
    ]

}